ringer/__init__.py
ringer/__main__.py
ringer/exceptions.py
ringer/manager.py
ringer/rings.py
ringer/storages.py
ringer/version.py
ringer/collections/__init__.py
ringer/collections/base.py
ringer/collections/deques.py
ringer/collections/lists.py
ringer/collections/sequences.py
ringer-0.0.4.dist-info/LICENSE
ringer-0.0.4.dist-info/METADATA
ringer-0.0.4.dist-info/WHEEL
ringer-0.0.4.dist-info/top_level.txt
ringer-0.0.4.dist-info/RECORD
