Metadata-Version: 2.1
Name: ringer
Version: 0.0.4
Summary: Large-scale data structures hosted on the file-system
Home-page: https://github.com/garciparedes/ringer
Author: Sergio García Prado
Author-email: sergio@garciparedes.me
License: UNKNOWN
Platform: UNKNOWN
